cofferfile/__init__.py
cofferfile/decorator.py
cofferfile/zstd.py
cofferfile-0.0.10.dist-info/METADATA
cofferfile-0.0.10.dist-info/WHEEL
cofferfile-0.0.10.dist-info/licenses/LICENSE
cofferfile-0.0.10.dist-info/RECORD
